hellorota/__init__.py
hellorota/core.py
hellorota-0.1.2.dist-info/METADATA
hellorota-0.1.2.dist-info/WHEEL
hellorota-0.1.2.dist-info/top_level.txt
hellorota-0.1.2.dist-info/RECORD
