Metadata-Version: 2.4
Name: hellorota
Version: 0.1.2
Summary: Funzione HelloWorld con effetto typing
Home-page: 
Author: Rotafn
Author-email: rotafn@vortexmc.it
Classifier: Programming Language :: Python :: 3
Classifier: Operating System :: OS Independent
Dynamic: author
Dynamic: author-email
Dynamic: classifier
Dynamic: summary
